multiagent_inspect/__init__.py
multiagent_inspect/core.py
multiagent_inspect-0.0.7.dist-info/METADATA
multiagent_inspect-0.0.7.dist-info/WHEEL
multiagent_inspect-0.0.7.dist-info/licenses/LICENSE
multiagent_inspect-0.0.7.dist-info/RECORD
