Metadata-Version: 2.4
Name: multiagent-inspect
Version: 0.0.7
Summary: Multi-agent system for AI evaluations in AISI's inspect-ai framework
Project-URL: Homepage, https://github.com/AndonLabs/multiagent-inspect
Author-email: Lukas Petersson <lukas.petersson.1999@gmail.com>
License: Apache-2.0
License-File: LICENSE
Requires-Dist: inspect-ai
